{
 "entities": {
  "Fh1KS4je0sazt1Q_0": {
   "transform": {
    "origin": {
     "y": 0.0,
     "x": 0.0,
     "z": 0.0
    },
    "y_axis": {
     "y": 1.0,
     "x": 0.0,
     "z": 0.0
    },
    "x_axis": {
     "y": 0.0,
     "x": 1.0,
     "z": 0.0
    },
    "z_axis": {
     "y": 0.0,
     "x": 0.0,
     "z": 1.0
    }
   },
   "type": "Sketch",
   "name": "Sketch 1",
   "profiles": {
    "JGK": {
     "loops": [
      {
       "is_outer": true,
       "profile_curves": [
        {
         "center_point": {
          "y": -0.01,
          "x": -0.01,
          "z": 0.0
         },
         "type": "Circle3D",
         "radius": 0.003,
         "curve": "KGhB",
         "normal": {
          "y": 0.0,
          "x": 0.0,
          "z": -1.0
         }
        }
       ]
      }
     ],
     "properties": {}
    },
    "JGO": {
     "loops": [
      {
       "is_outer": true,
       "profile_curves": [
        {
         "center_point": {
          "y": 0.0,
          "x": 0.03,
          "z": 0.0
         },
         "type": "Circle3D",
         "radius": 0.0025,
         "curve": "KGFC",
         "normal": {
          "y": 0.0,
          "x": 0.0,
          "z": -1.0
         }
        }
       ]
      }
     ],
     "properties": {}
    },
    "JGa": {
     "loops": [
      {
       "is_outer": true,
       "profile_curves": [
        {
         "center_point": {
          "y": 0.00592047,
          "x": 0.00590098,
          "z": 0.0
         },
         "normal": {
          "y": 0.0,
          "x": 0.0,
          "z": 1.0
         },
         "end_point": {
          "y": 0.00592047,
          "x": 0.00690098,
          "z": 0.0
         },
         "start_angle": 0.0,
         "curve": "KGdE",
         "end_angle": 0.7705484000429896,
         "radius": 0.001,
         "type": "Arc3D",
         "start_point": {
          "y": 0.00522394,
          "x": 0.00661851,
          "z": 0.0
         },
         "reference_vector": {
          "y": -0.6965288361709397,
          "x": 0.7175288010821279,
          "z": 0.0
         }
        },
        {
         "type": "Line3D",
         "start_point": {
          "y": 0.00592047,
          "x": 0.00690098,
          "z": 0.0
         },
         "curve": "KGVE",
         "end_point": {
          "y": 0.0115,
          "x": 0.00690098,
          "z": 0.0
         }
        },
        {
         "center_point": {
          "y": 0.0115,
          "x": 0.00790098,
          "z": 0.0
         },
         "normal": {
          "y": 0.0,
          "x": 0.0,
          "z": 1.0
         },
         "end_point": {
          "y": 0.0125,
          "x": 0.00790098,
          "z": 0.0
         },
         "start_angle": 0.0,
         "curve": "KGhE",
         "end_angle": 1.5707963267948966,
         "radius": 0.001,
         "type": "Arc3D",
         "start_point": {
          "y": 0.0115,
          "x": 0.00690098,
          "z": 0.0
         },
         "reference_vector": {
          "y": 1.0,
          "x": 0.0,
          "z": 0.0
         }
        },
        {
         "type": "Line3D",
         "start_point": {
          "y": 0.0125,
          "x": 0.00790098,
          "z": 0.0
         },
         "curve": "KGZE",
         "end_point": {
          "y": 0.0125,
          "x": 0.015,
          "z": 0.0
         }
        },
        {
         "type": "Line3D",
         "start_point": {
          "y": 0.0125,
          "x": 0.015,
          "z": 0.0
         },
         "curve": "KGlE",
         "end_point": {
          "y": 0.0125,
          "x": 0.02209902,
          "z": 0.0
         }
        },
        {
         "center_point": {
          "y": 0.0115,
          "x": 0.02209902,
          "z": 0.0
         },
         "normal": {
          "y": 0.0,
          "x": 0.0,
          "z": -1.0
         },
         "end_point": {
          "y": 0.0115,
          "x": 0.02309902,
          "z": 0.0
         },
         "start_angle": 0.0,
         "curve": "KGpE",
         "end_angle": 1.5707963267948966,
         "radius": 0.001,
         "type": "Arc3D",
         "start_point": {
          "y": 0.0125,
          "x": 0.02209902,
          "z": 0.0
         },
         "reference_vector": {
          "y": 0.0,
          "x": 1.0,
          "z": 0.0
         }
        },
        {
         "type": "Line3D",
         "start_point": {
          "y": 0.0115,
          "x": 0.02309902,
          "z": 0.0
         },
         "curve": "KGtE",
         "end_point": {
          "y": 0.00592047,
          "x": 0.02309902,
          "z": 0.0
         }
        },
        {
         "center_point": {
          "y": 0.00592047,
          "x": 0.02409902,
          "z": 0.0
         },
         "normal": {
          "y": 0.0,
          "x": 0.0,
          "z": -1.0
         },
         "end_point": {
          "y": 0.00522394,
          "x": 0.02338149,
          "z": 0.0
         },
         "start_angle": 0.0,
         "curve": "KGxE",
         "end_angle": 0.7705484000429919,
         "radius": 0.001,
         "type": "Arc3D",
         "start_point": {
          "y": 0.00592047,
          "x": 0.02309902,
          "z": 0.0
         },
         "reference_vector": {
          "y": 0.0,
          "x": -1.0,
          "z": 0.0
         }
        },
        {
         "center_point": {
          "y": 0.0,
          "x": 0.018,
          "z": 0.0
         },
         "radius": 0.0075,
         "normal": {
          "y": 0.0,
          "x": 0.0,
          "z": -1.0
         },
         "curve": "KGdF+KG1E",
         "start_angle": 0.0,
         "end_angle": 1.5410873170337882,
         "type": "Arc3D",
         "start_point": {
          "x": 0.023381490777627866,
          "y": -0.0052239407548618135,
          "z": 0.0
         },
         "end_point": {
          "x": 0.023381490777627863,
          "y": 0.005223940754861814,
          "z": 0.0
         },
         "reference_vector": {
          "x": 0.7175321036837156,
          "y": -0.6965254339815752,
          "z": 0.0
         }
        },
        {
         "center_point": {
          "y": -0.00592047,
          "x": 0.02409902,
          "z": 0.0
         },
         "normal": {
          "y": 0.0,
          "x": 0.0,
          "z": 1.0
         },
         "end_point": {
          "y": -0.00522394,
          "x": 0.02338149,
          "z": 0.0
         },
         "start_angle": 0.0,
         "curve": "KGZF",
         "end_angle": 0.7705484000429919,
         "radius": 0.001,
         "type": "Arc3D",
         "start_point": {
          "y": -0.00592047,
          "x": 0.02309902,
          "z": 0.0
         },
         "reference_vector": {
          "y": 0.6965288361709411,
          "x": -0.7175288010821267,
          "z": 0.0
         }
        },
        {
         "type": "Line3D",
         "start_point": {
          "y": -0.0115,
          "x": 0.02309902,
          "z": 0.0
         },
         "curve": "KGVF",
         "end_point": {
          "y": -0.00592047,
          "x": 0.02309902,
          "z": 0.0
         }
        },
        {
         "center_point": {
          "y": -0.0115,
          "x": 0.02209902,
          "z": 0.0
         },
         "normal": {
          "y": 0.0,
          "x": 0.0,
          "z": 1.0
         },
         "end_point": {
          "y": -0.0115,
          "x": 0.02309902,
          "z": 0.0
         },
         "start_angle": 0.0,
         "curve": "KGRF",
         "end_angle": 1.5707963267948966,
         "radius": 0.001,
         "type": "Arc3D",
         "start_point": {
          "y": -0.0125,
          "x": 0.02209902,
          "z": 0.0
         },
         "reference_vector": {
          "y": -1.0,
          "x": 0.0,
          "z": 0.0
         }
        },
        {
         "type": "Line3D",
         "start_point": {
          "y": -0.0125,
          "x": 0.015,
          "z": 0.0
         },
         "curve": "KGNF",
         "end_point": {
          "y": -0.0125,
          "x": 0.02209902,
          "z": 0.0
         }
        },
        {
         "type": "Line3D",
         "start_point": {
          "y": -0.0125,
          "x": 0.00790098,
          "z": 0.0
         },
         "curve": "KGFF",
         "end_point": {
          "y": -0.0125,
          "x": 0.015,
          "z": 0.0
         }
        },
        {
         "center_point": {
          "y": -0.0115,
          "x": 0.00790098,
          "z": 0.0
         },
         "normal": {
          "y": 0.0,
          "x": 0.0,
          "z": -1.0
         },
         "end_point": {
          "y": -0.0125,
          "x": 0.00790098,
          "z": 0.0
         },
         "start_angle": 0.0,
         "curve": "KGJF",
         "end_angle": 1.5707963267948966,
         "radius": 0.001,
         "type": "Arc3D",
         "start_point": {
          "y": -0.0115,
          "x": 0.00690098,
          "z": 0.0
         },
         "reference_vector": {
          "y": 0.0,
          "x": -1.0,
          "z": 0.0
         }
        },
        {
         "type": "Line3D",
         "start_point": {
          "y": -0.00592047,
          "x": 0.00690098,
          "z": 0.0
         },
         "curve": "KGBF",
         "end_point": {
          "y": -0.0115,
          "x": 0.00690098,
          "z": 0.0
         }
        },
        {
         "center_point": {
          "y": -0.00592047,
          "x": 0.00590098,
          "z": 0.0
         },
         "normal": {
          "y": 0.0,
          "x": 0.0,
          "z": -1.0
         },
         "end_point": {
          "y": -0.00592047,
          "x": 0.00690098,
          "z": 0.0
         },
         "start_angle": 0.0,
         "curve": "KG9E",
         "end_angle": 0.7705484000429899,
         "radius": 0.001,
         "type": "Arc3D",
         "start_point": {
          "y": -0.00522394,
          "x": 0.00661851,
          "z": 0.0
         },
         "reference_vector": {
          "y": 0.0,
          "x": 1.0,
          "z": 0.0
         }
        },
        {
         "center_point": {
          "y": 0.0,
          "x": 0.012,
          "z": 0.0
         },
         "radius": 0.0075,
         "normal": {
          "y": 0.0,
          "x": 0.0,
          "z": -1.0
         },
         "curve": "KGRE+KG5E",
         "start_angle": 0.0,
         "end_angle": 1.5410873170337887,
         "type": "Arc3D",
         "start_point": {
          "x": 0.0066185092223721344,
          "y": 0.005223940754861815,
          "z": 0.0
         },
         "end_point": {
          "x": 0.006618509222372135,
          "y": -0.005223940754861817,
          "z": 0.0
         },
         "reference_vector": {
          "x": -0.7175321036837154,
          "y": 0.6965254339815754,
          "z": 0.0
         }
        }
       ]
      }
     ],
     "properties": {}
    },
    "JGC": {
     "loops": [
      {
       "is_outer": true,
       "profile_curves": [
        {
         "center_point": {
          "y": 0.0,
          "x": 0.0,
          "z": 0.0
         },
         "type": "Circle3D",
         "radius": 0.0025,
         "curve": "JGB",
         "normal": {
          "y": 0.0,
          "x": 0.0,
          "z": 1.0
         }
        }
       ]
      }
     ],
     "properties": {}
    },
    "JGe": {
     "loops": [
      {
       "is_outer": true,
       "profile_curves": [
        {
         "center_point": {
          "y": 0.0,
          "x": 0.0,
          "z": 0.0
         },
         "type": "Circle3D",
         "radius": 0.0025,
         "curve": "JGB",
         "normal": {
          "y": 0.0,
          "x": 0.0,
          "z": 1.0
         }
        }
       ]
      },
      {
       "is_outer": true,
       "profile_curves": [
        {
         "center_point": {
          "y": 0.01,
          "x": -0.01,
          "z": 0.0
         },
         "type": "Circle3D",
         "radius": 0.003,
         "curve": "JGF",
         "normal": {
          "y": 0.0,
          "x": 0.0,
          "z": 1.0
         }
        }
       ]
      },
      {
       "is_outer": true,
       "profile_curves": [
        {
         "type": "Line3D",
         "start_point": {
          "y": 0.0145,
          "x": -0.015,
          "z": 0.0
         },
         "curve": "JGJ",
         "end_point": {
          "y": 0.00315,
          "x": -0.015,
          "z": 0.0
         }
        },
        {
         "type": "Line3D",
         "start_point": {
          "y": 0.00315,
          "x": -0.015,
          "z": 0.0
         },
         "curve": "JGN",
         "end_point": {
          "y": 0.00315,
          "x": -0.0125,
          "z": 0.0
         }
        },
        {
         "type": "Line3D",
         "start_point": {
          "y": 0.00315,
          "x": -0.0125,
          "z": 0.0
         },
         "curve": "JGR",
         "end_point": {
          "y": 0.0055,
          "x": -0.0125,
          "z": 0.0
         }
        },
        {
         "type": "Line3D",
         "start_point": {
          "y": 0.0055,
          "x": -0.0125,
          "z": 0.0
         },
         "curve": "JGZ",
         "end_point": {
          "y": 0.0055,
          "x": -0.00690098,
          "z": 0.0
         }
        },
        {
         "center_point": {
          "y": 0.0,
          "x": -0.012,
          "z": 0.0
         },
         "radius": 0.0075,
         "normal": {
          "y": 0.0,
          "x": 0.0,
          "z": -1.0
         },
         "curve": "JG1+JGV",
         "start_angle": 0.0,
         "end_angle": 1.6464238591321223,
         "type": "Arc3D",
         "start_point": {
          "x": -0.006900980224828241,
          "y": -0.005499999757491571,
          "z": 0.0
         },
         "end_point": {
          "x": -0.00690098022482824,
          "y": 0.0054999997574915705,
          "z": 0.0
         },
         "reference_vector": {
          "x": 0.6798693033562345,
          "y": -0.7333333009988762,
          "z": 0.0
         }
        },
        {
         "type": "Line3D",
         "start_point": {
          "y": -0.0055,
          "x": -0.00690098,
          "z": 0.0
         },
         "curve": "JG5",
         "end_point": {
          "y": -0.0055,
          "x": -0.0125,
          "z": 0.0
         }
        },
        {
         "type": "Line3D",
         "start_point": {
          "y": -0.0055,
          "x": -0.0125,
          "z": 0.0
         },
         "curve": "JG9",
         "end_point": {
          "y": -0.00315,
          "x": -0.0125,
          "z": 0.0
         }
        },
        {
         "type": "Line3D",
         "start_point": {
          "y": -0.00315,
          "x": -0.0125,
          "z": 0.0
         },
         "curve": "KGBB",
         "end_point": {
          "y": -0.00315,
          "x": -0.015,
          "z": 0.0
         }
        },
        {
         "type": "Line3D",
         "start_point": {
          "y": -0.00315,
          "x": -0.015,
          "z": 0.0
         },
         "curve": "KGFB",
         "end_point": {
          "y": -0.0145,
          "x": -0.015,
          "z": 0.0
         }
        },
        {
         "center_point": {
          "y": -0.0145,
          "x": -0.0145,
          "z": 0.0
         },
         "normal": {
          "y": 0.0,
          "x": 0.0,
          "z": -1.0
         },
         "end_point": {
          "y": -0.015,
          "x": -0.0145,
          "z": 0.0
         },
         "start_angle": 0.0,
         "curve": "KGJB",
         "end_angle": 1.5707963267948966,
         "radius": 0.0005,
         "type": "Arc3D",
         "start_point": {
          "y": -0.0145,
          "x": -0.015,
          "z": 0.0
         },
         "reference_vector": {
          "y": 0.0,
          "x": -1.0,
          "z": 0.0
         }
        },
        {
         "type": "Line3D",
         "start_point": {
          "y": -0.015,
          "x": -0.0145,
          "z": 0.0
         },
         "curve": "KGNB",
         "end_point": {
          "y": -0.015,
          "x": -0.00315,
          "z": 0.0
         }
        },
        {
         "type": "Line3D",
         "start_point": {
          "y": -0.015,
          "x": -0.00315,
          "z": 0.0
         },
         "curve": "KGRB",
         "end_point": {
          "y": -0.0125,
          "x": -0.00315,
          "z": 0.0
         }
        },
        {
         "type": "Line3D",
         "start_point": {
          "y": -0.0125,
          "x": -0.00315,
          "z": 0.0
         },
         "curve": "KGVB",
         "end_point": {
          "y": -0.0125,
          "x": -0.0055,
          "z": 0.0
         }
        },
        {
         "type": "Line3D",
         "start_point": {
          "y": -0.0125,
          "x": -0.0055,
          "z": 0.0
         },
         "curve": "KGZB",
         "end_point": {
          "y": -0.00690098,
          "x": -0.0055,
          "z": 0.0
         }
        },
        {
         "center_point": {
          "y": -0.012,
          "x": 0.0,
          "z": 0.0
         },
         "radius": 0.0075,
         "normal": {
          "y": 0.0,
          "x": 0.0,
          "z": -1.0
         },
         "curve": "KG1B+KGdB",
         "start_angle": 0.0,
         "end_angle": 1.6464238591321223,
         "type": "Arc3D",
         "start_point": {
          "x": 0.005499999757491571,
          "y": -0.006900980224828241,
          "z": 0.0
         },
         "end_point": {
          "x": -0.0054999997574915705,
          "y": -0.00690098022482824,
          "z": 0.0
         },
         "reference_vector": {
          "x": 0.7333333009988762,
          "y": 0.6798693033562345,
          "z": 0.0
         }
        },
        {
         "type": "Line3D",
         "start_point": {
          "y": -0.00690098,
          "x": 0.0055,
          "z": 0.0
         },
         "curve": "KG5B",
         "end_point": {
          "y": -0.0125,
          "x": 0.0055,
          "z": 0.0
         }
        },
        {
         "type": "Line3D",
         "start_point": {
          "y": -0.0125,
          "x": 0.0055,
          "z": 0.0
         },
         "curve": "KG9B",
         "end_point": {
          "y": -0.0125,
          "x": 0.00315,
          "z": 0.0
         }
        },
        {
         "type": "Line3D",
         "start_point": {
          "y": -0.0125,
          "x": 0.00315,
          "z": 0.0
         },
         "curve": "KGBC",
         "end_point": {
          "y": -0.015,
          "x": 0.00315,
          "z": 0.0
         }
        },
        {
         "type": "Line3D",
         "start_point": {
          "y": -0.015,
          "x": 0.00315,
          "z": 0.0
         },
         "curve": "KGNE",
         "end_point": {
          "y": -0.015,
          "x": 0.02685,
          "z": 0.0
         }
        },
        {
         "type": "Line3D",
         "start_point": {
          "y": -0.0125,
          "x": 0.02685,
          "z": 0.0
         },
         "curve": "KG9D",
         "end_point": {
          "y": -0.015,
          "x": 0.02685,
          "z": 0.0
         }
        },
        {
         "type": "Line3D",
         "start_point": {
          "y": -0.0125,
          "x": 0.0245,
          "z": 0.0
         },
         "curve": "KG5D",
         "end_point": {
          "y": -0.0125,
          "x": 0.02685,
          "z": 0.0
         }
        },
        {
         "type": "Line3D",
         "start_point": {
          "y": -0.00690098,
          "x": 0.0245,
          "z": 0.0
         },
         "curve": "KG1D",
         "end_point": {
          "y": -0.0125,
          "x": 0.0245,
          "z": 0.0
         }
        },
        {
         "center_point": {
          "y": -0.012,
          "x": 0.03,
          "z": 0.0
         },
         "radius": 0.0075,
         "normal": {
          "y": 0.0,
          "x": 0.0,
          "z": -1.0
         },
         "curve": "KGtD+KGxD",
         "start_angle": 0.0,
         "end_angle": 1.6464238591321223,
         "type": "Arc3D",
         "start_point": {
          "x": 0.03549999975749157,
          "y": -0.00690098022482824,
          "z": 0.0
         },
         "end_point": {
          "x": 0.024500000242508427,
          "y": -0.006900980224828241,
          "z": 0.0
         },
         "reference_vector": {
          "x": 0.7333333009988761,
          "y": 0.6798693033562346,
          "z": 0.0
         }
        },
        {
         "type": "Line3D",
         "start_point": {
          "y": -0.0125,
          "x": 0.0355,
          "z": 0.0
         },
         "curve": "KGpD",
         "end_point": {
          "y": -0.00690098,
          "x": 0.0355,
          "z": 0.0
         }
        },
        {
         "type": "Line3D",
         "start_point": {
          "y": -0.0125,
          "x": 0.03315,
          "z": 0.0
         },
         "curve": "KGlD",
         "end_point": {
          "y": -0.0125,
          "x": 0.0355,
          "z": 0.0
         }
        },
        {
         "type": "Line3D",
         "start_point": {
          "y": -0.015,
          "x": 0.03315,
          "z": 0.0
         },
         "curve": "KGhD",
         "end_point": {
          "y": -0.0125,
          "x": 0.03315,
          "z": 0.0
         }
        },
        {
         "type": "Line3D",
         "start_point": {
          "y": -0.015,
          "x": 0.0445,
          "z": 0.0
         },
         "curve": "KGdD",
         "end_point": {
          "y": -0.015,
          "x": 0.03315,
          "z": 0.0
         }
        },
        {
         "center_point": {
          "y": -0.0145,
          "x": 0.0445,
          "z": 0.0
         },
         "normal": {
          "y": 0.0,
          "x": 0.0,
          "z": 1.0
         },
         "end_point": {
          "y": -0.015,
          "x": 0.0445,
          "z": 0.0
         },
         "start_angle": 0.0,
         "curve": "KGZD",
         "end_angle": 1.5707963267948966,
         "radius": 0.0005,
         "type": "Arc3D",
         "start_point": {
          "y": -0.0145,
          "x": 0.045,
          "z": 0.0
         },
         "reference_vector": {
          "y": -1.0,
          "x": 0.0,
          "z": 0.0
         }
        },
        {
         "type": "Line3D",
         "start_point": {
          "y": -0.00315,
          "x": 0.045,
          "z": 0.0
         },
         "curve": "KGVD",
         "end_point": {
          "y": -0.0145,
          "x": 0.045,
          "z": 0.0
         }
        },
        {
         "type": "Line3D",
         "start_point": {
          "y": -0.00315,
          "x": 0.0425,
          "z": 0.0
         },
         "curve": "KGRD",
         "end_point": {
          "y": -0.00315,
          "x": 0.045,
          "z": 0.0
         }
        },
        {
         "type": "Line3D",
         "start_point": {
          "y": -0.0055,
          "x": 0.0425,
          "z": 0.0
         },
         "curve": "KGND",
         "end_point": {
          "y": -0.00315,
          "x": 0.0425,
          "z": 0.0
         }
        },
        {
         "type": "Line3D",
         "start_point": {
          "y": -0.0055,
          "x": 0.03690098,
          "z": 0.0
         },
         "curve": "KGJD",
         "end_point": {
          "y": -0.0055,
          "x": 0.0425,
          "z": 0.0
         }
        },
        {
         "center_point": {
          "y": 0.0,
          "x": 0.042,
          "z": 0.0
         },
         "radius": 0.0075,
         "normal": {
          "y": 0.0,
          "x": 0.0,
          "z": -1.0
         },
         "curve": "KGBD+KGFD",
         "start_angle": 0.0,
         "end_angle": 1.6464238591321223,
         "type": "Arc3D",
         "start_point": {
          "x": 0.03690098022482824,
          "y": 0.0054999997574915705,
          "z": 0.0
         },
         "end_point": {
          "x": 0.036900980224828246,
          "y": -0.005499999757491572,
          "z": 0.0
         },
         "reference_vector": {
          "x": -0.6798693033562347,
          "y": 0.7333333009988761,
          "z": 0.0
         }
        },
        {
         "type": "Line3D",
         "start_point": {
          "y": 0.0055,
          "x": 0.0425,
          "z": 0.0
         },
         "curve": "KG9C",
         "end_point": {
          "y": 0.0055,
          "x": 0.03690098,
          "z": 0.0
         }
        },
        {
         "type": "Line3D",
         "start_point": {
          "y": 0.00315,
          "x": 0.0425,
          "z": 0.0
         },
         "curve": "KG5C",
         "end_point": {
          "y": 0.0055,
          "x": 0.0425,
          "z": 0.0
         }
        },
        {
         "type": "Line3D",
         "start_point": {
          "y": 0.00315,
          "x": 0.045,
          "z": 0.0
         },
         "curve": "KG1C",
         "end_point": {
          "y": 0.00315,
          "x": 0.0425,
          "z": 0.0
         }
        },
        {
         "type": "Line3D",
         "start_point": {
          "y": 0.0145,
          "x": 0.045,
          "z": 0.0
         },
         "curve": "KGxC",
         "end_point": {
          "y": 0.00315,
          "x": 0.045,
          "z": 0.0
         }
        },
        {
         "center_point": {
          "y": 0.0145,
          "x": 0.0445,
          "z": 0.0
         },
         "normal": {
          "y": 0.0,
          "x": 0.0,
          "z": -1.0
         },
         "end_point": {
          "y": 0.0145,
          "x": 0.045,
          "z": 0.0
         },
         "start_angle": 0.0,
         "curve": "KGtC",
         "end_angle": 1.5707963267948966,
         "radius": 0.0005,
         "type": "Arc3D",
         "start_point": {
          "y": 0.015,
          "x": 0.0445,
          "z": 0.0
         },
         "reference_vector": {
          "y": 0.0,
          "x": 1.0,
          "z": 0.0
         }
        },
        {
         "type": "Line3D",
         "start_point": {
          "y": 0.015,
          "x": 0.03315,
          "z": 0.0
         },
         "curve": "KGpC",
         "end_point": {
          "y": 0.015,
          "x": 0.0445,
          "z": 0.0
         }
        },
        {
         "type": "Line3D",
         "start_point": {
          "y": 0.0125,
          "x": 0.03315,
          "z": 0.0
         },
         "curve": "KGlC",
         "end_point": {
          "y": 0.015,
          "x": 0.03315,
          "z": 0.0
         }
        },
        {
         "type": "Line3D",
         "start_point": {
          "y": 0.0125,
          "x": 0.0355,
          "z": 0.0
         },
         "curve": "KGhC",
         "end_point": {
          "y": 0.0125,
          "x": 0.03315,
          "z": 0.0
         }
        },
        {
         "type": "Line3D",
         "start_point": {
          "y": 0.00690098,
          "x": 0.0355,
          "z": 0.0
         },
         "curve": "KGdC",
         "end_point": {
          "y": 0.0125,
          "x": 0.0355,
          "z": 0.0
         }
        },
        {
         "center_point": {
          "y": 0.012,
          "x": 0.03,
          "z": 0.0
         },
         "radius": 0.0075,
         "normal": {
          "y": 0.0,
          "x": 0.0,
          "z": -1.0
         },
         "curve": "KGVC+KGZC",
         "start_angle": 0.0,
         "end_angle": 1.6464238591321223,
         "type": "Arc3D",
         "start_point": {
          "x": 0.024500000242508427,
          "y": 0.00690098022482824,
          "z": 0.0
         },
         "end_point": {
          "x": 0.035499999757491574,
          "y": 0.006900980224828241,
          "z": 0.0
         },
         "reference_vector": {
          "x": -0.7333333009988761,
          "y": -0.6798693033562346,
          "z": 0.0
         }
        },
        {
         "type": "Line3D",
         "start_point": {
          "y": 0.0125,
          "x": 0.0245,
          "z": 0.0
         },
         "curve": "KGRC",
         "end_point": {
          "y": 0.00690098,
          "x": 0.0245,
          "z": 0.0
         }
        },
        {
         "type": "Line3D",
         "start_point": {
          "y": 0.0125,
          "x": 0.02685,
          "z": 0.0
         },
         "curve": "KGNC",
         "end_point": {
          "y": 0.0125,
          "x": 0.0245,
          "z": 0.0
         }
        },
        {
         "type": "Line3D",
         "start_point": {
          "y": 0.015,
          "x": 0.02685,
          "z": 0.0
         },
         "curve": "KGJC",
         "end_point": {
          "y": 0.0125,
          "x": 0.02685,
          "z": 0.0
         }
        },
        {
         "type": "Line3D",
         "start_point": {
          "y": 0.015,
          "x": 0.00315,
          "z": 0.0
         },
         "curve": "KGJE",
         "end_point": {
          "y": 0.015,
          "x": 0.02685,
          "z": 0.0
         }
        },
        {
         "type": "Line3D",
         "start_point": {
          "y": 0.0125,
          "x": 0.00315,
          "z": 0.0
         },
         "curve": "KGxB",
         "end_point": {
          "y": 0.015,
          "x": 0.00315,
          "z": 0.0
         }
        },
        {
         "type": "Line3D",
         "start_point": {
          "y": 0.0125,
          "x": 0.0055,
          "z": 0.0
         },
         "curve": "KGtB",
         "end_point": {
          "y": 0.0125,
          "x": 0.00315,
          "z": 0.0
         }
        },
        {
         "type": "Line3D",
         "start_point": {
          "y": 0.00690098,
          "x": 0.0055,
          "z": 0.0
         },
         "curve": "KGpB",
         "end_point": {
          "y": 0.0125,
          "x": 0.0055,
          "z": 0.0
         }
        },
        {
         "center_point": {
          "y": 0.012,
          "x": 0.0,
          "z": 0.0
         },
         "radius": 0.0075,
         "normal": {
          "y": 0.0,
          "x": 0.0,
          "z": -1.0
         },
         "curve": "JGx+KGlB",
         "start_angle": 0.0,
         "end_angle": 1.6464238591321223,
         "type": "Arc3D",
         "start_point": {
          "x": -0.005499999757491571,
          "y": 0.006900980224828241,
          "z": 0.0
         },
         "end_point": {
          "x": 0.0054999997574915705,
          "y": 0.00690098022482824,
          "z": 0.0
         },
         "reference_vector": {
          "x": -0.7333333009988762,
          "y": -0.6798693033562345,
          "z": 0.0
         }
        },
        {
         "type": "Line3D",
         "start_point": {
          "y": 0.0125,
          "x": -0.0055,
          "z": 0.0
         },
         "curve": "JGt",
         "end_point": {
          "y": 0.00690098,
          "x": -0.0055,
          "z": 0.0
         }
        },
        {
         "type": "Line3D",
         "start_point": {
          "y": 0.0125,
          "x": -0.00315,
          "z": 0.0
         },
         "curve": "JGp",
         "end_point": {
          "y": 0.0125,
          "x": -0.0055,
          "z": 0.0
         }
        },
        {
         "type": "Line3D",
         "start_point": {
          "y": 0.015,
          "x": -0.00315,
          "z": 0.0
         },
         "curve": "JGl",
         "end_point": {
          "y": 0.0125,
          "x": -0.00315,
          "z": 0.0
         }
        },
        {
         "type": "Line3D",
         "start_point": {
          "y": 0.015,
          "x": -0.0145,
          "z": 0.0
         },
         "curve": "JGd",
         "end_point": {
          "y": 0.015,
          "x": -0.00315,
          "z": 0.0
         }
        },
        {
         "center_point": {
          "y": 0.0145,
          "x": -0.0145,
          "z": 0.0
         },
         "normal": {
          "y": 0.0,
          "x": 0.0,
          "z": 1.0
         },
         "end_point": {
          "y": 0.015,
          "x": -0.0145,
          "z": 0.0
         },
         "start_angle": 0.0,
         "curve": "JGh",
         "end_angle": 1.5707963267948966,
         "radius": 0.0005,
         "type": "Arc3D",
         "start_point": {
          "y": 0.0145,
          "x": -0.015,
          "z": 0.0
         },
         "reference_vector": {
          "y": 1.0,
          "x": 0.0,
          "z": 0.0
         }
        }
       ]
      },
      {
       "is_outer": true,
       "profile_curves": [
        {
         "center_point": {
          "y": -0.01,
          "x": -0.01,
          "z": 0.0
         },
         "type": "Circle3D",
         "radius": 0.003,
         "curve": "KGhB",
         "normal": {
          "y": 0.0,
          "x": 0.0,
          "z": -1.0
         }
        }
       ]
      },
      {
       "is_outer": true,
       "profile_curves": [
        {
         "center_point": {
          "y": 0.0,
          "x": 0.03,
          "z": 0.0
         },
         "type": "Circle3D",
         "radius": 0.0025,
         "curve": "KGFC",
         "normal": {
          "y": 0.0,
          "x": 0.0,
          "z": -1.0
         }
        }
       ]
      },
      {
       "is_outer": true,
       "profile_curves": [
        {
         "center_point": {
          "y": -0.01,
          "x": 0.04,
          "z": 0.0
         },
         "type": "Circle3D",
         "radius": 0.003,
         "curve": "KGBE",
         "normal": {
          "y": 0.0,
          "x": 0.0,
          "z": 1.0
         }
        }
       ]
      },
      {
       "is_outer": true,
       "profile_curves": [
        {
         "center_point": {
          "y": 0.01,
          "x": 0.04,
          "z": 0.0
         },
         "type": "Circle3D",
         "radius": 0.003,
         "curve": "KGFE",
         "normal": {
          "y": 0.0,
          "x": 0.0,
          "z": -1.0
         }
        }
       ]
      },
      {
       "is_outer": true,
       "profile_curves": [
        {
         "center_point": {
          "y": 0.00592047,
          "x": 0.00590098,
          "z": 0.0
         },
         "normal": {
          "y": 0.0,
          "x": 0.0,
          "z": 1.0
         },
         "end_point": {
          "y": 0.00592047,
          "x": 0.00690098,
          "z": 0.0
         },
         "start_angle": 0.0,
         "curve": "KGdE",
         "end_angle": 0.7705484000429896,
         "radius": 0.001,
         "type": "Arc3D",
         "start_point": {
          "y": 0.00522394,
          "x": 0.00661851,
          "z": 0.0
         },
         "reference_vector": {
          "y": -0.6965288361709397,
          "x": 0.7175288010821279,
          "z": 0.0
         }
        },
        {
         "type": "Line3D",
         "start_point": {
          "y": 0.00592047,
          "x": 0.00690098,
          "z": 0.0
         },
         "curve": "KGVE",
         "end_point": {
          "y": 0.0115,
          "x": 0.00690098,
          "z": 0.0
         }
        },
        {
         "center_point": {
          "y": 0.0115,
          "x": 0.00790098,
          "z": 0.0
         },
         "normal": {
          "y": 0.0,
          "x": 0.0,
          "z": 1.0
         },
         "end_point": {
          "y": 0.0125,
          "x": 0.00790098,
          "z": 0.0
         },
         "start_angle": 0.0,
         "curve": "KGhE",
         "end_angle": 1.5707963267948966,
         "radius": 0.001,
         "type": "Arc3D",
         "start_point": {
          "y": 0.0115,
          "x": 0.00690098,
          "z": 0.0
         },
         "reference_vector": {
          "y": 1.0,
          "x": 0.0,
          "z": 0.0
         }
        },
        {
         "type": "Line3D",
         "start_point": {
          "y": 0.0125,
          "x": 0.00790098,
          "z": 0.0
         },
         "curve": "KGZE",
         "end_point": {
          "y": 0.0125,
          "x": 0.015,
          "z": 0.0
         }
        },
        {
         "type": "Line3D",
         "start_point": {
          "y": 0.0125,
          "x": 0.015,
          "z": 0.0
         },
         "curve": "KGlE",
         "end_point": {
          "y": 0.0125,
          "x": 0.02209902,
          "z": 0.0
         }
        },
        {
         "center_point": {
          "y": 0.0115,
          "x": 0.02209902,
          "z": 0.0
         },
         "normal": {
          "y": 0.0,
          "x": 0.0,
          "z": -1.0
         },
         "end_point": {
          "y": 0.0115,
          "x": 0.02309902,
          "z": 0.0
         },
         "start_angle": 0.0,
         "curve": "KGpE",
         "end_angle": 1.5707963267948966,
         "radius": 0.001,
         "type": "Arc3D",
         "start_point": {
          "y": 0.0125,
          "x": 0.02209902,
          "z": 0.0
         },
         "reference_vector": {
          "y": 0.0,
          "x": 1.0,
          "z": 0.0
         }
        },
        {
         "type": "Line3D",
         "start_point": {
          "y": 0.0115,
          "x": 0.02309902,
          "z": 0.0
         },
         "curve": "KGtE",
         "end_point": {
          "y": 0.00592047,
          "x": 0.02309902,
          "z": 0.0
         }
        },
        {
         "center_point": {
          "y": 0.00592047,
          "x": 0.02409902,
          "z": 0.0
         },
         "normal": {
          "y": 0.0,
          "x": 0.0,
          "z": -1.0
         },
         "end_point": {
          "y": 0.00522394,
          "x": 0.02338149,
          "z": 0.0
         },
         "start_angle": 0.0,
         "curve": "KGxE",
         "end_angle": 0.7705484000429919,
         "radius": 0.001,
         "type": "Arc3D",
         "start_point": {
          "y": 0.00592047,
          "x": 0.02309902,
          "z": 0.0
         },
         "reference_vector": {
          "y": 0.0,
          "x": -1.0,
          "z": 0.0
         }
        },
        {
         "center_point": {
          "y": 0.0,
          "x": 0.018,
          "z": 0.0
         },
         "radius": 0.0075,
         "normal": {
          "y": 0.0,
          "x": 0.0,
          "z": -1.0
         },
         "curve": "KGdF+KG1E",
         "start_angle": 0.0,
         "end_angle": 1.5410873170337882,
         "type": "Arc3D",
         "start_point": {
          "x": 0.023381490777627866,
          "y": -0.0052239407548618135,
          "z": 0.0
         },
         "end_point": {
          "x": 0.023381490777627863,
          "y": 0.005223940754861814,
          "z": 0.0
         },
         "reference_vector": {
          "x": 0.7175321036837156,
          "y": -0.6965254339815752,
          "z": 0.0
         }
        },
        {
         "center_point": {
          "y": -0.00592047,
          "x": 0.02409902,
          "z": 0.0
         },
         "normal": {
          "y": 0.0,
          "x": 0.0,
          "z": 1.0
         },
         "end_point": {
          "y": -0.00522394,
          "x": 0.02338149,
          "z": 0.0
         },
         "start_angle": 0.0,
         "curve": "KGZF",
         "end_angle": 0.7705484000429919,
         "radius": 0.001,
         "type": "Arc3D",
         "start_point": {
          "y": -0.00592047,
          "x": 0.02309902,
          "z": 0.0
         },
         "reference_vector": {
          "y": 0.6965288361709411,
          "x": -0.7175288010821267,
          "z": 0.0
         }
        },
        {
         "type": "Line3D",
         "start_point": {
          "y": -0.0115,
          "x": 0.02309902,
          "z": 0.0
         },
         "curve": "KGVF",
         "end_point": {
          "y": -0.00592047,
          "x": 0.02309902,
          "z": 0.0
         }
        },
        {
         "center_point": {
          "y": -0.0115,
          "x": 0.02209902,
          "z": 0.0
         },
         "normal": {
          "y": 0.0,
          "x": 0.0,
          "z": 1.0
         },
         "end_point": {
          "y": -0.0115,
          "x": 0.02309902,
          "z": 0.0
         },
         "start_angle": 0.0,
         "curve": "KGRF",
         "end_angle": 1.5707963267948966,
         "radius": 0.001,
         "type": "Arc3D",
         "start_point": {
          "y": -0.0125,
          "x": 0.02209902,
          "z": 0.0
         },
         "reference_vector": {
          "y": -1.0,
          "x": 0.0,
          "z": 0.0
         }
        },
        {
         "type": "Line3D",
         "start_point": {
          "y": -0.0125,
          "x": 0.015,
          "z": 0.0
         },
         "curve": "KGNF",
         "end_point": {
          "y": -0.0125,
          "x": 0.02209902,
          "z": 0.0
         }
        },
        {
         "type": "Line3D",
         "start_point": {
          "y": -0.0125,
          "x": 0.00790098,
          "z": 0.0
         },
         "curve": "KGFF",
         "end_point": {
          "y": -0.0125,
          "x": 0.015,
          "z": 0.0
         }
        },
        {
         "center_point": {
          "y": -0.0115,
          "x": 0.00790098,
          "z": 0.0
         },
         "normal": {
          "y": 0.0,
          "x": 0.0,
          "z": -1.0
         },
         "end_point": {
          "y": -0.0125,
          "x": 0.00790098,
          "z": 0.0
         },
         "start_angle": 0.0,
         "curve": "KGJF",
         "end_angle": 1.5707963267948966,
         "radius": 0.001,
         "type": "Arc3D",
         "start_point": {
          "y": -0.0115,
          "x": 0.00690098,
          "z": 0.0
         },
         "reference_vector": {
          "y": 0.0,
          "x": -1.0,
          "z": 0.0
         }
        },
        {
         "type": "Line3D",
         "start_point": {
          "y": -0.00592047,
          "x": 0.00690098,
          "z": 0.0
         },
         "curve": "KGBF",
         "end_point": {
          "y": -0.0115,
          "x": 0.00690098,
          "z": 0.0
         }
        },
        {
         "center_point": {
          "y": -0.00592047,
          "x": 0.00590098,
          "z": 0.0
         },
         "normal": {
          "y": 0.0,
          "x": 0.0,
          "z": -1.0
         },
         "end_point": {
          "y": -0.00592047,
          "x": 0.00690098,
          "z": 0.0
         },
         "start_angle": 0.0,
         "curve": "KG9E",
         "end_angle": 0.7705484000429899,
         "radius": 0.001,
         "type": "Arc3D",
         "start_point": {
          "y": -0.00522394,
          "x": 0.00661851,
          "z": 0.0
         },
         "reference_vector": {
          "y": 0.0,
          "x": 1.0,
          "z": 0.0
         }
        },
        {
         "center_point": {
          "y": 0.0,
          "x": 0.012,
          "z": 0.0
         },
         "radius": 0.0075,
         "normal": {
          "y": 0.0,
          "x": 0.0,
          "z": -1.0
         },
         "curve": "KGRE+KG5E",
         "start_angle": 0.0,
         "end_angle": 1.5410873170337887,
         "type": "Arc3D",
         "start_point": {
          "x": 0.0066185092223721344,
          "y": 0.005223940754861815,
          "z": 0.0
         },
         "end_point": {
          "x": 0.006618509222372135,
          "y": -0.005223940754861817,
          "z": 0.0
         },
         "reference_vector": {
          "x": -0.7175321036837154,
          "y": 0.6965254339815754,
          "z": 0.0
         }
        }
       ]
      }
     ],
     "properties": {}
    },
    "JGG": {
     "loops": [
      {
       "is_outer": true,
       "profile_curves": [
        {
         "center_point": {
          "y": 0.01,
          "x": -0.01,
          "z": 0.0
         },
         "type": "Circle3D",
         "radius": 0.003,
         "curve": "JGF",
         "normal": {
          "y": 0.0,
          "x": 0.0,
          "z": 1.0
         }
        }
       ]
      }
     ],
     "properties": {}
    },
    "JGS": {
     "loops": [
      {
       "is_outer": true,
       "profile_curves": [
        {
         "center_point": {
          "y": -0.01,
          "x": 0.04,
          "z": 0.0
         },
         "type": "Circle3D",
         "radius": 0.003,
         "curve": "KGBE",
         "normal": {
          "y": 0.0,
          "x": 0.0,
          "z": 1.0
         }
        }
       ]
      }
     ],
     "properties": {}
    },
    "JGW": {
     "loops": [
      {
       "is_outer": true,
       "profile_curves": [
        {
         "center_point": {
          "y": 0.01,
          "x": 0.04,
          "z": 0.0
         },
         "type": "Circle3D",
         "radius": 0.003,
         "curve": "KGFE",
         "normal": {
          "y": 0.0,
          "x": 0.0,
          "z": -1.0
         }
        }
       ]
      }
     ],
     "properties": {}
    }
   },
   "reference_plane": {}
  },
  "FdkFkLb7Z3SjcRP_0": {
   "name": "3060 * 500mm",
   "type": "ExtrudeFeature",
   "profiles": [
    {
     "profile": "JGe",
     "sketch": "Fh1KS4je0sazt1Q_0"
    }
   ],
   "extent_two": {
    "distance": {
     "type": "ModelParameter",
     "role": "AgainstDistance",
     "name": "none",
     "value": 0.0
    },
    "type": "DistanceExtentDefinition",
    "taper_angle": {
     "type": "ModelParameter",
     "role": "Side2TaperAngle",
     "name": "none",
     "value": 0.0
    }
   },
   "extent_one": {
    "distance": {
     "type": "ModelParameter",
     "role": "AlongDistance",
     "name": "none",
     "value": 0.5
    },
    "type": "DistanceExtentDefinition",
    "taper_angle": {
     "type": "ModelParameter",
     "role": "TaperAngle",
     "name": "none",
     "value": 0.0
    }
   },
   "operation": "NewBodyFeatureOperation",
   "start_extent": {
    "type": "ProfilePlaneStartDefinition"
   },
   "extent_type": "OneSideFeatureExtentType"
  },
  "FFAvEFSqocHdrbo_0": {
   "name": "3060 * 480mm",
   "type": "ExtrudeFeature",
   "profiles": [
    {
     "profile": "JGe",
     "sketch": "Fh1KS4je0sazt1Q_0"
    }
   ],
   "extent_two": {
    "distance": {
     "type": "ModelParameter",
     "role": "AgainstDistance",
     "name": "none",
     "value": 0.0
    },
    "type": "DistanceExtentDefinition",
    "taper_angle": {
     "type": "ModelParameter",
     "role": "Side2TaperAngle",
     "name": "none",
     "value": 0.0
    }
   },
   "extent_one": {
    "distance": {
     "type": "ModelParameter",
     "role": "AlongDistance",
     "name": "none",
     "value": 0.48
    },
    "type": "DistanceExtentDefinition",
    "taper_angle": {
     "type": "ModelParameter",
     "role": "TaperAngle",
     "name": "none",
     "value": 0.0
    }
   },
   "operation": "NewBodyFeatureOperation",
   "start_extent": {
    "type": "ProfilePlaneStartDefinition"
   },
   "extent_type": "OneSideFeatureExtentType"
  }
 },
 "properties": {
  "bounding_box": {
   "max_point": {
    "y": 0.015000000000000001,
    "x": 0.04499999999999999,
    "z": 0.5
   },
   "type": "BoundingBox3D",
   "min_point": {
    "y": -0.015000000000000003,
    "x": -0.014999999999999998,
    "z": 0.0
   }
  }
 },
 "sequence": [
  {
   "index": 0,
   "type": "Sketch",
   "entity": "Fh1KS4je0sazt1Q_0"
  },
  {
   "index": 1,
   "type": "ExtrudeFeature",
   "entity": "FdkFkLb7Z3SjcRP_0"
  },
  {
   "index": 2,
   "type": "ExtrudeFeature",
   "entity": "FFAvEFSqocHdrbo_0"
  }
 ]
}